randomcoords/__init__.py
randomcoords/core.py
randomcoords/types.py
randomcoords-1.0.2.dist-info/licenses/LICENSE
tests/test_core.py
randomcoords-1.0.2.dist-info/METADATA
randomcoords-1.0.2.dist-info/WHEEL
randomcoords-1.0.2.dist-info/top_level.txt
randomcoords-1.0.2.dist-info/RECORD
