Metadata-Version: 2.4
Name: randomcoords
Version: 1.0.2
Summary: The Python client for the RandomCoords API to fetch random geographic coordinates worldwide.
Author-email: Talha Awan <talha@talhaawan.net>
License: MIT
Project-URL: Homepage, https://github.com/talhaawan/randomcoords-python
Keywords: api,random,geographic,location,coordinates,latitude,longitude,world,regions,countries
Classifier: Development Status :: 5 - Production/Stable
Classifier: Intended Audience :: Developers
Classifier: Programming Language :: Python :: 3
Classifier: Programming Language :: Python :: 3.8
Classifier: Programming Language :: Python :: 3.9
Classifier: Programming Language :: Python :: 3.10
Classifier: Programming Language :: Python :: 3.11
Classifier: Programming Language :: Python :: 3.12
Classifier: Programming Language :: Python :: 3.13
Classifier: Topic :: Software Development :: Libraries :: Python Modules
Requires-Python: >=3.8
License-File: LICENSE
Provides-Extra: dev
Requires-Dist: pytest; extra == "dev"
Requires-Dist: python-dotenv; extra == "dev"
Requires-Dist: mypy; extra == "dev"
Requires-Dist: ruff; extra == "dev"
Dynamic: license-file
